d08/__init__.py
d08/asgi.py
d08/settings.py
d08/urls.py
d08/wsgi.py
ex/__init__.py
ex/admin.py
ex/apps.py
ex/forms.py
ex/models.py
ex/tests.py
ex/urls.py
ex/views.py
ex/migrations/0001_initial.py
ex/migrations/__init__.py
ukim42d08-0.1.data/scripts/manage.py
ukim42d08-0.1.dist-info/METADATA
ukim42d08-0.1.dist-info/WHEEL
ukim42d08-0.1.dist-info/top_level.txt
ukim42d08-0.1.dist-info/RECORD
