Metadata-Version: 2.1
Name: ukim42d08
Version: 0.1
Summary: Django-based project boilerplate that follows best practices
Home-page: https://www.example.com/
Author: John Doe
Author-email: test@exmaple.com
License: MIT
Platform: UNKNOWN
Classifier: Development Status :: 3 - Alpha
Classifier: Framework :: Django
Classifier: Intended Audience :: Developers
Classifier: Topic :: Software Development :: Build Tools
Classifier: License :: OSI Approved :: MIT License
Classifier: Programming Language :: Python :: 2
Classifier: Programming Language :: Python :: 2.7
Classifier: Programming Language :: Python :: 3
Classifier: Programming Language :: Python :: 3.4
Classifier: Programming Language :: Python :: 3.5
Classifier: Programming Language :: Python :: 3.6
Requires-Dist: Django
Requires-Dist: django-crispy-forms
